pncp/__init__.py
pncp/tipos.py
pncp/utils.py
pncp/instrumentos_convocatorios/__init__.py
pncp/instrumentos_convocatorios/busca.py
pncp/instrumentos_convocatorios/tipos.py
pncp-0.1.1.dist-info/METADATA
pncp-0.1.1.dist-info/WHEEL
pncp-0.1.1.dist-info/RECORD
