Metadata-Version: 2.4
Name: pncp
Version: 0.1.1
Summary: Ferramenta para facilitar pesquisas ao Portal Nacional de Contratações Públicas (PNCP).
Author: Otávio Barradas
License-Expression: MIT
Keywords: API,Brazil,PNCP,Python,public procurement
Classifier: License :: OSI Approved :: MIT License
Classifier: Operating System :: OS Independent
Classifier: Programming Language :: Python :: 3
Classifier: Topic :: Software Development :: Libraries :: Python Modules
Requires-Python: ~=3.12.0
Requires-Dist: httpx>=0.28.1
Requires-Dist: pydantic>=2.11.4
